README.rst
setup.py
JpTokenPreprocessing.egg-info/PKG-INFO
JpTokenPreprocessing.egg-info/SOURCES.txt
JpTokenPreprocessing.egg-info/dependency_links.txt
JpTokenPreprocessing.egg-info/top_level.txt
jp_token_preprocessing/__init__.py