Metadata-Version: 1.1
Name: JpTokenPreprocessing
Version: 0.1.3a
Summary: JpTokenPreprocessing is Python library for token preprocessing.
Home-page: https://github.com/Kesin11/JpTokenPreprocessing
Author: Kenta Kase
Author-email: kesin1202000@gmail.com
License: MIT
Download-URL: https://github.com/Kesin11/JpTokenPreprocessing/archive/master.zip
Keywords: NLP,natural language processing,token,japaneese
Platform: UNKNOWN
Classifier: Development Status :: 3 - Alpha
Classifier: Intended Audience :: Developers
Classifier: Intended Audience :: Science/Research
Classifier: Intended Audience :: Information Technology
Classifier: License :: OSI Approved :: MIT License
Classifier: Topic :: System :: Operating System Kernels :: Linux
Classifier: Topic :: Scientific/Engineering :: Artificial Intelligence
Classifier: Topic :: Text Processing
Classifier: Topic :: Text Processing :: Filters
Classifier: Natural Language :: Japanese
Classifier: Programming Language :: Python :: 3.3
Classifier: Programming Language :: Python :: 3.4
